wiretaps/__init__.py
wiretaps/api.py
wiretaps/cli.py
wiretaps/dashboard.py
wiretaps/pii.py
wiretaps/proxy.py
wiretaps/storage.py
wiretaps-0.7.0.dist-info/METADATA
wiretaps-0.7.0.dist-info/WHEEL
wiretaps-0.7.0.dist-info/entry_points.txt
wiretaps-0.7.0.dist-info/licenses/LICENSE
wiretaps-0.7.0.dist-info/RECORD
