Metadata-Version: 2.4
Name: wiretaps
Version: 0.7.0
Summary: See what your AI agents are sending to LLMs. MitM proxy for auditing, PII detection, and compliance.
Project-URL: Homepage, https://wiretaps.ai
Project-URL: Documentation, https://wiretaps.ai/docs
Project-URL: Repository, https://github.com/marcosgabbardo/wiretaps
Project-URL: Issues, https://github.com/marcosgabbardo/wiretaps/issues
Author-email: Marcos Gabbardo <mgabbardo@protonmail.com>
License-Expression: MIT
License-File: LICENSE
Keywords: ai-agents,anthropic,audit,compliance,llm,openai,pii,proxy,security
Classifier: Development Status :: 3 - Alpha
Classifier: Environment :: Console
Classifier: Intended Audience :: Developers
Classifier: License :: OSI Approved :: MIT License
Classifier: Operating System :: OS Independent
Classifier: Programming Language :: Python :: 3
Classifier: Programming Language :: Python :: 3.11
Classifier: Programming Language :: Python :: 3.12
Classifier: Programming Language :: Python :: 3.13
Classifier: Topic :: Security
Classifier: Topic :: Software Development :: Libraries :: Python Modules
Requires-Python: >=3.11
Requires-Dist: aiohttp>=3.9.0
Requires-Dist: click>=8.1.0
Requires-Dist: pyyaml>=6.0
Requires-Dist: rich>=13.0.0
Requires-Dist: textual>=0.47.0
Provides-Extra: dev
Requires-Dist: mypy>=1.8.0; extra == 'dev'
Requires-Dist: pytest-asyncio>=0.23.0; extra == 'dev'
Requires-Dist: pytest-cov>=4.1.0; extra == 'dev'
Requires-Dist: pytest>=8.0.0; extra == 'dev'
Requires-Dist: ruff>=0.2.0; extra == 'dev'
Provides-Extra: spacy
Requires-Dist: spacy>=3.7.0; extra == 'spacy'
